CTkFileDialog/Dialog.py
CTkFileDialog/__init__.py
CTkFileDialog/_functions.py
CTkFileDialog/_system.py
CTkFileDialog/Constants/__init__.py
CTkFileDialog/Constants/constants.py
CTkFileDialog/icons/bash.png
CTkFileDialog/icons/conf.png
CTkFileDialog/icons/css.png
CTkFileDialog/icons/exe.png
CTkFileDialog/icons/folder.png
CTkFileDialog/icons/gz.png
CTkFileDialog/icons/html.png
CTkFileDialog/icons/image.png
CTkFileDialog/icons/ini.png
CTkFileDialog/icons/javascript.png
CTkFileDialog/icons/js.png
CTkFileDialog/icons/json.png
CTkFileDialog/icons/markdown.png
CTkFileDialog/icons/odt.png
CTkFileDialog/icons/pdf.png
CTkFileDialog/icons/php.png
CTkFileDialog/icons/python.png
CTkFileDialog/icons/text.png
CTkFileDialog/icons/video.png
CTkFileDialog/icons/_IconsMini/file.png
CTkFileDialog/icons/_IconsMini/folder.png
ctkfiledialog-0.3.3.dist-info/METADATA
ctkfiledialog-0.3.3.dist-info/WHEEL
ctkfiledialog-0.3.3.dist-info/top_level.txt
ctkfiledialog-0.3.3.dist-info/RECORD
