Metadata-Version: 2.4
Name: CTkFileDialog
Version: 0.3.3
Home-page: https://github.com/FlickGMD/CTkFileDialog
Author: Flick
Requires-Dist: customtkinter
Requires-Dist: CTkMessagebox
Requires-Dist: Pillow
Requires-Dist: opencv-python
Requires-Dist: CTkToolTip
Requires-Dist: typeguard
Dynamic: author
Dynamic: description
Dynamic: description-content-type
Dynamic: home-page
Dynamic: requires-dist
